odoo/addons/sale_order_report_product_image/README.rst
odoo/addons/sale_order_report_product_image/__init__.py
odoo/addons/sale_order_report_product_image/__manifest__.py
odoo/addons/sale_order_report_product_image/i18n/de.po
odoo/addons/sale_order_report_product_image/i18n/es.po
odoo/addons/sale_order_report_product_image/i18n/it.po
odoo/addons/sale_order_report_product_image/i18n/pt.po
odoo/addons/sale_order_report_product_image/i18n/sale_order_report_product_image.pot
odoo/addons/sale_order_report_product_image/i18n/tr.po
odoo/addons/sale_order_report_product_image/readme/CONTRIBUTORS.md
odoo/addons/sale_order_report_product_image/readme/DESCRIPTION.md
odoo/addons/sale_order_report_product_image/readme/INSTALL.md
odoo/addons/sale_order_report_product_image/readme/USAGE.md
odoo/addons/sale_order_report_product_image/static/description/icon.png
odoo/addons/sale_order_report_product_image/static/description/index.html
odoo/addons/sale_order_report_product_image/views/report_saleorder.xml
odoo_addon_sale_order_report_product_image-18.0.1.0.2.dist-info/METADATA
odoo_addon_sale_order_report_product_image-18.0.1.0.2.dist-info/WHEEL
odoo_addon_sale_order_report_product_image-18.0.1.0.2.dist-info/top_level.txt
odoo_addon_sale_order_report_product_image-18.0.1.0.2.dist-info/RECORD
